ecs_service/__init__.py
ecs_service/ecs_service_stack.py
ecs_service-0.1.0.dist-info/LICENSE
ecs_service-0.1.0.dist-info/METADATA
ecs_service-0.1.0.dist-info/WHEEL
ecs_service-0.1.0.dist-info/top_level.txt
ecs_service-0.1.0.dist-info/RECORD
